{
  "etag": "7266988792719311874",
  "channelId": "komei.official",
  "channelTitle": "\u516c\u660e\u515a",
  "description": "\u516c\u5f0f\u30a2\u30ab\u30a6\u30f3\u30c8\u3067\u3059\u2600\ufe0f\n\u516c\u660e\u515a\u306e\u8b70\u54e1\u306b\u8272\u3005\u805e\u3044\u3066\u307f\u305f\uff01\n\u3067\u304d\u308b\u3060\u3051\u308f\u304b\u308a\u3084\u3059\u304f\u9811\u5f35\u308a\u307e\u3059\ud83d\udcaa\ud83c\udffb\ud83d\udd25",
  "thumbnails": "https://p16-sign-sg.tiktokcdn.com/aweme/1080x1080/tos-alisg-avt-0068/9b79634fa1677b4b8965134623d61b33.jpeg?x-expires=1696572000&x-signature=ap7twpBahRZujcUmI61eiBSaEJk%3D",
  "link": "",
  "commerceUser": false,
  "likeCount": 0,
  "followerCount": 8638,
  "followingCount": 0,
  "heartCount": 73500,
  "videoCount": 25
}